pytelemetry/__init__.py
pytelemetry/pytelemetry.py
pytelemetry/remoting.py
pytelemetry/telemetry/__init__.py
pytelemetry/telemetry/c_binding.py
pytelemetry/telemetry/crc.py
pytelemetry/telemetry/framing.py
pytelemetry/telemetry/telemetry.py
pytelemetry/test/__init__.py
pytelemetry/test/test_loopedback.py
pytelemetry/test/test_pure_decoding.py
pytelemetry/test/test_serialTransport.py
pytelemetry/test/test_telemetry_direct.py
pytelemetry/test/test_translate.py
pytelemetry/test/test_typing.py
pytelemetry/transports/__init__.py
pytelemetry/transports/serialtransport.py
pytelemetry-1.1.9.dist-info/DESCRIPTION.rst
pytelemetry-1.1.9.dist-info/METADATA
pytelemetry-1.1.9.dist-info/RECORD
pytelemetry-1.1.9.dist-info/WHEEL
pytelemetry-1.1.9.dist-info/metadata.json
pytelemetry-1.1.9.dist-info/top_level.txt
